{"stats":{"minecraft:killed_by":{"minecraft:player":8,"minecraft:wither_skeleton":5,"minecraft:creeper":2,"minecraft:spider":1,"minecraft:iron_golem":4,"enemyexpansion:goblin":1,"minecraft:slime":1,"undead_unleashed:frenzied_knight":1,"minecraft:skeleton":2,"minecraft:phantom":5,"majruszsdifficulty:cursed_armor":2},"minecraft:used":{"minecraft:netherite_sword":6,"minecraft:trident":2,"simplyswords:iron_claymore":77,"minecraft:stone_sword":13,"minecraft:spruce_planks":17,"woodworks:spruce_chest":2,"minecraft:dirt":1,"minecraft:spyglass":2,"minecraft:anvil":2,"minecraft:pink_terracotta":2,"minecraft:bookshelf":5,"minecraft:quartz_pillar":1,"minecraft:iron_axe":87,"minecraft:smooth_sandstone":25,"ars_nouveau:green_archwood_sapling":1,"minecraft:furnace":1,"minecraft:stone_pickaxe":26,"minecraft:ender_pearl":1,"minecraft:wooden_pickaxe":3,"minecraft:green_bed":1,"minecraft:smooth_quartz_stairs":3,"minecraft:golden_apple":14,"minecraft:terracotta":1,"minecraft:crafting_table":5,"aether:life_shard":3,"atmospheric:aspen_planks":7,"simplyswords:diamond_claymore":50,"minecraft:oak_log":1,"farmersdelight:ratatouille":3,"minecraft:diamond_pickaxe":7,"waystones:mossy_waystone":2,"minecraft:iron_pickaxe":44,"minecraft:wooden_sword":15,"minecraft:cobblestone":16,"minecraft:potion":1,"ars_nouveau:scribes_table":1,"minecraft:enchanting_table":1,"irons_spellbooks:inscription_table":1},"minecraft:broken":{"immersive_armors:wooden_chestplate":1,"immersive_armors:wooden_leggings":1,"immersive_armors:wooden_boots":1,"alexsmobs:fedora":1},"minecraft:dropped":{"byg:biomepedia":1,"minecraft:iron_ingot":19,"minecraft:bread":22,"knightlib:small_essence":10,"cisco_mod:adventurer_helmet":2,"byg:blueberries":2,"minecraft:porkchop":5,"minecraft:wheat_seeds":1,"minecraft:lapis_lazuli":1,"minecolonies:scroll_buff":17,"atmospheric:aspen_planks":4,"minecraft:ender_pearl":1,"minecraft:glass_bottle":5,"minecraft:diamond":11,"majruszsaccessories:adventurer_kit":1,"minecraft:diamond_leggings":1,"minecraft:crossbow":1,"minecraft:iron_helmet":2,"minecraft:book":2,"relics:infinity_ham":3,"minecraft:apple":10,"cisco_mod:adventurer_leggings":2,"undead_unleashed:grave_metal_scrap":2,"minecraft:copper_ingot":2,"cisco_mod:adventurer_chestplate":1,"minecraft:leather_helmet":1,"minecraft:golden_apple":20,"minecraft:flint":1,"minecraft:stick":13,"minecraft:deepslate_tile_stairs":1,"enigmaticlegacy:enigmatic_eye":1,"ars_nouveau:worn_notebook":1,"relics:leather_belt":2,"farmersdelight:golden_knife":1,"minecraft:diorite":16,"immersive_armors:wooden_leggings":1,"forbidden_arcanus:spawner_scrap":8,"minecraft:diamond_helmet":2,"minecraft:iron_leggings":1,"farmersdelight:bacon":5,"irons_spellbooks:common_ink":1,"minecraft:sand":5,"quark:jasper":4,"minecraft:iron_pickaxe":1,"minecraft:smooth_sandstone":9,"minecraft:bucket":1,"minecraft:bone":1,"minecraft:gold_ingot":27,"twigs:twig":2,"relics:wool_mitten":2,"minecraft:dark_oak_door":2,"minecraft:spyglass":2,"cisco_mod:adventurer_boots":2,"minecraft:iron_nugget":11,"ars_nouveau:source_berry":24,"relics:hunter_belt":1,"minecraft:stone_sword":1,"alexsmobs:animal_dictionary":1,"minecraft:bowl":2,"ringsofascension:ring_growth":1,"enigmaticlegacy:soul_crystal":20,"minecraft:beetroot":4,"minecraft:rotten_flesh":17,"minecraft:grindstone":2,"enigmaticlegacy:tattered_tome":5,"waystones:sandy_waystone":1,"iter_rpg:spawner_fragment":7,"irons_spellbooks:inscription_table":1,"minecraft:carrot":11,"patchouli:guide_book":3,"enigmaticlegacy:cursed_ring":3,"minecraft:deepslate_bricks":3,"minecraft:poppy":2,"minecraft:leather_chestplate":1,"minecraft:potato":38,"minecraft:tipped_arrow":8,"minecraft:gray_terracotta":3,"minecraft:turtle_helmet":1,"minecraft:shield":1,"minecraft:trident":2,"minecraft:gunpowder":13,"aether:iron_gloves":1,"minecraft:spruce_planks":13,"minecraft:diamond_pickaxe":1,"minecraft:iron_chestplate":1,"iter_rpg:iron_flail":1,"minecraft:beetroot_seeds":12,"apotheosis:gem":1,"quark:blank_rune":1,"minecraft:leather_boots":1,"minecraft:oak_sapling":1,"minecraft:chainmail_boots":3,"simplyswords:iron_longsword":1,"farmersdelight:bacon_and_eggs":32,"minecraft:leather_leggings":2,"minecraft:spider_eye":1,"minecraft:diamond_boots":2,"minecraft:slime_ball":1,"minecraft:iron_bars":2,"minecraft:arrow":14,"minecraft:bow":1,"ars_nouveau:mendosteen_pod":3,"minecraft:wooden_pickaxe":1,"atmospheric:aspen_log":1,"farmersdelight:ratatouille":28,"minecraft:cracked_deepslate_bricks":1,"ars_nouveau:amplify_arrow":31,"minecraft:ghast_tear":2,"enigmaticlegacy:enigmatic_amulet":3,"immersive_armors:wooden_helmet":3,"simplyswords:iron_claymore":2,"ars_nouveau:novice_spell_book":1,"minecraft:enchanted_book":1},"minecraft:killed":{"minecraft:spider":1,"enemyexpansion:direwolf":1,"minecraft:slime":16,"minecraft:skeleton":4,"minecraft:bee":2,"ecologics:coconut_crab":2,"minecraft:pig":3,"minecraft:iron_golem":2,"minecraft:creeper":9,"minecraft:zombie":5,"iter_rpg:goblin_warrior":1},"minecraft:custom":{"minecraft:interact_with_anvil":4,"minecraft:interact_with_smithing_table":1,"enigmaticlegacy:play_time_with_seven_curses":179895,"lootr:looted_stat":79,"minecraft:mob_kills":46,"minecraft:interact_with_crafting_table":43,"minecraft:open_barrel":8,"minecraft:leave_game":1,"minecraft:damage_dealt_resisted":0,"minecraft:time_since_death":12699,"minecraft:climb_one_cm":15666,"minecraft:damage_resisted":0,"minecraft:sprint_one_cm":384559,"minecraft:walk_one_cm":426227,"minecraft:drop":203,"minecraft:talked_to_villager":1,"minecraft:play_time":185907,"minecraft:deaths":39,"minecraft:sneak_time":2287,"minecraft:walk_under_water_one_cm":17851,"minecraft:boat_one_cm":2795,"minecraft:jump":1732,"minecraft:interact_with_brewingstand":1,"minecraft:interact_with_blast_furnace":2,"minecraft:walk_on_water_one_cm":26849,"minecraft:total_world_time":188520,"minecraft:interact_with_furnace":1,"enigmaticlegacy:play_time_without_seven_curses":4807,"minecraft:tune_noteblock":5,"minecraft:sleep_in_bed":4,"minecraft:time_since_rest":12730,"minecraft:waystone_activated":2,"minecraft:damage_absorbed":392,"minecraft:damage_taken":12798,"minecraft:trigger_trapped_chest":2,"minecraft:damage_dealt":8564,"minecraft:swim_one_cm":15164,"minecraft:fly_one_cm":424747,"minecraft:open_chest":35,"minecraft:crouch_one_cm":9223,"minecraft:aviate_one_cm":627702,"minecraft:fall_one_cm":31825},"minecraft:picked_up":{"iter_rpg:spawner_fragment":7,"minecraft:crafting_table":3,"minecraft:chainmail_boots":3,"minecraft:turtle_helmet":1,"minecolonies:scroll_buff":6,"aether:iron_gloves":1,"minecraft:potion":3,"enigmaticlegacy:tattered_tome":4,"minecraft:brewing_stand":1,"minecraft:string":10,"skilltree:wisdom_scroll":1,"relics:leather_belt":1,"minecraft:raw_copper":16,"irons_spellbooks:nature_rune":1,"atmospheric:aspen_log":1,"minecraft:beetroot":4,"irons_spellbooks:arcane_essence":2,"minecraft:diamond_leggings":1,"twigs:pebble":1,"minecraft:spruce_planks":15,"irons_spellbooks:epic_ink":1,"immersive_armors:wooden_leggings":1,"ars_nouveau:mendosteen_pod":3,"minecraft:poppy":4,"minecraft:sugar_cane":13,"ars_nouveau:conjuration_essence":3,"irons_spellbooks:inscription_table":2,"minecraft:smooth_quartz_stairs":3,"atmospheric:aspen_planks":11,"knightlib:small_essence":9,"minecraft:furnace":1,"minecraft:dark_oak_door":2,"minecraft:sandstone":2,"minecraft:stick":2,"apotheosis:gem":1,"ecologics:coconut_slice":4,"minecraft:copper_ingot":2,"minecraft:green_bed":1,"ars_nouveau:blue_archwood_log":13,"minecraft:porkchop":5,"minecraft:quartz_pillar":1,"minecraft:diorite":16,"minecraft:carrot":11,"majruszsaccessories:adventurer_kit":1,"minecraft:deepslate_tile_stairs":1,"minecraft:pink_terracotta":2,"ars_nouveau:green_archwood_log":56,"minecraft:arrow":14,"immersive_armors:wooden_helmet":2,"minecraft:rotten_flesh":18,"minecraft:beetroot_seeds":12,"minecraft:diamond_boots":1,"minecraft:deepslate_bricks":3,"minecraft:cracked_deepslate_bricks":1,"minecraft:saddle":1,"minecraft:iron_bars":2,"forbidden_arcanus:spawner_scrap":8,"enigmaticlegacy:soul_crystal":7,"minecraft:cobblestone":19,"minecraft:leather_chestplate":1,"minecraft:flint":1,"waystones:sandy_waystone":2,"simplyswords:iron_claymore":1,"minecraft:oak_log":1,"minecraft:gunpowder":78,"minecraft:lapis_lazuli":2,"minecraft:dirt":1,"ars_nouveau:green_archwood_sapling":5,"minecraft:leather_boots":1,"irons_spellbooks:rare_ink":2,"minecraft:smooth_sandstone":20,"irons_spellbooks:common_ink":1,"minecraft:bone":3,"ars_nouveau:water_essence":1,"minecraft:gray_terracotta":3,"minecraft:wheat_seeds":1,"byg:blueberries":2,"iter_rpg:potsherd":5,"minecraft:spruce_wood":1,"minecraft:iron_ingot":4,"minecraft:grindstone":2,"minecraft:diamond_helmet":1,"iter_rpg:iron_flail":1,"minecraft:glass_bottle":4,"twigs:twig":2,"minecraft:book":6,"minecraft:ghast_tear":2,"relics:hunter_belt":1,"waystones:mossy_waystone":1,"minecraft:spyglass":1,"ars_nouveau:novice_spell_book":1,"minecraft:sand":5,"enigmaticlegacy:enigmatic_amulet":2,"undead_unleashed:grave_metal_scrap":2,"minecraft:spruce_log":13,"minecraft:spider_eye":1,"minecraft:leather_helmet":1,"quark:jasper":4,"simplyswords:diamond_claymore":1,"enigmaticlegacy:cursed_ring":1,"minecraft:purple_bed":1,"minecraft:slime_ball":3,"minecraft:lever":1,"minecraft:iron_helmet":1,"minecraft:golden_apple":15,"minecraft:terracotta":1,"minecraft:oak_sapling":1,"minecraft:stripped_dark_oak_log":1,"minecraft:leather_leggings":2,"minecraft:anvil":1,"minecraft:diamond_pickaxe":4},"minecraft:crafted":{"ars_nouveau:archwood_planks":4,"woodworks:spruce_chest":2,"irons_spellbooks:copper_spell_book":1,"minecraft:cauldron":1,"minecraft:crafting_table":1,"minecraft:spruce_planks":44,"minecraft:anvil":1},"minecraft:mined":{"minecraft:spruce_planks":5,"minecraft:brewing_stand":1,"minecraft:grass_block":1,"minecraft:deepslate_bricks":3,"minecraft:deepslate_tile_stairs":1,"minecraft:spruce_leaves":2,"ars_nouveau:sourceberry_bush":1,"minecraft:spawner":11,"minecraft:furnace":1,"iter_rpg:small_vase":4,"minecraft:anvil":1,"minecraft:bookshelf":1,"minecraft:iron_bars":2,"minecraft:spruce_wood":1,"irons_spellbooks:inscription_table":1,"minecraft:stone":16,"minecraft:pink_terracotta":4,"atmospheric:aspen_planks":7,"twigs:pebble":1,"ars_nouveau:green_archwood_log":56,"minecraft:stripped_dark_oak_log":1,"minecraft:smooth_sandstone":20,"minecraft:crafting_table":2,"iter_rpg:vase":2,"minecraft:copper_ore":2,"minecraft:sugar_cane":3,"minecraft:grindstone":1,"minecraft:cracked_deepslate_bricks":1,"minecraft:diorite":1,"ars_nouveau:blue_archwood_log":13,"minecraft:purple_bed":1,"minecraft:spruce_log":13,"minecraft:quartz_pillar":1,"minecraft:grass":2,"minecraft:oak_log":1,"minecraft:beetroots":3,"minecraft:sand":5,"minecraft:terracotta":1,"minecraft:fern":1}},"DataVersion":3120}